jnjrender/__init__.py
jnjrender/cli.py
jnjrender/renderer.py
tests/__init__.py
tests/test_renderer.py
jnjrender-1.0.11.dist-info/METADATA
jnjrender-1.0.11.dist-info/WHEEL
jnjrender-1.0.11.dist-info/entry_points.txt
jnjrender-1.0.11.dist-info/top_level.txt
jnjrender-1.0.11.dist-info/RECORD
